{
  "sections": {
    "165176158934b1563a": {
      "type": "collection-list",
      "blocks": {
        "1651761589d29dd086-0": {
          "type": "featured_collection",
          "settings": {
            "collection": "orbit-1-exclusives"
          }
        },
        "1651761589d29dd086-1": {
          "type": "featured_collection",
          "settings": {
            "collection": "liftoff"
          }
        },
        "1651761589d29dd086-2": {
          "type": "featured_collection",
          "settings": {
            "collection": "total-look"
          }
        }
      },
      "block_order": [
        "1651761589d29dd086-0",
        "1651761589d29dd086-1",
        "1651761589d29dd086-2"
      ],
      "settings": {
        "title": "Collections"
      }
    },
    "banner": {
      "type": "main-collection-banner",
      "settings": {
        "show_collection_description": true,
        "show_collection_image": true,
        "color_scheme": "background-1"
      }
    },
    "product-grid": {
      "type": "main-collection-product-grid",
      "settings": {
        "collection_for_filter_list": [
          "total-look",
          "dress",
          "top",
          "jacket",
          "bottoms",
          "animal-wear",
          "accessory",
          "footwear",
          "143-dress",
          "dis_placed",
          "edvard-nielsen",
          "enye",
          "non-flam",
          "onclickcloset",
          "burbush",
          "ecoolska",
          "prep-corp",
          "olivia-goodall",
          "balmlabs"
        ]
      }
    },
    "1651428893f08018d8": {
      "type": "custom-liquid",
      "disabled": true,
      "settings": {
        "custom_liquid": "",
        "color_scheme": "background-1",
        "padding_top": 40,
        "padding_bottom": 52
      }
    }
  },
  "order": [
    "165176158934b1563a",
    "banner",
    "product-grid",
    "1651428893f08018d8"
  ]
}
